pandadock/__init__.py
pandadock/__main__.py
pandadock/config.py
pandadock/version.py
pandadock/docking/__init__.py
pandadock/docking/base_engine.py
pandadock/docking/flexible_docking.py
pandadock/docking/ga_engine.py
pandadock/docking/metal_coordination.py
pandadock/docking/metal_docking_engine.py
pandadock/docking/ml_engine.py
pandadock/docking/physics_engine.py
pandadock/docking/pose_filtering.py
pandadock/io/__init__.py
pandadock/io/ligand_preparer.py
pandadock/io/output_writer.py
pandadock/io/protein_preparer.py
pandadock/reports/__init__.py
pandadock/reports/html_report.py
pandadock/reports/interaction_analyzer.py
pandadock/reports/pandamap_integration.py
pandadock/reports/plot_generator.py
pandadock/scoring/__init__.py
pandadock/scoring/metal_scoring.py
pandadock/scoring/ml_rescorer.py
pandadock/scoring/scoring_functions.py
pandadock/utils/__init__.py
pandadock/utils/ic50_calculator.py
pandadock/utils/math_utils.py
pandadock/utils/metal_constraints.py
pandadock/utils/rotamer_lib.py
pandadock-2.6.0.dist-info/licenses/LICENSE
pandadock-2.6.0.dist-info/METADATA
pandadock-2.6.0.dist-info/WHEEL
pandadock-2.6.0.dist-info/entry_points.txt
pandadock-2.6.0.dist-info/top_level.txt
pandadock-2.6.0.dist-info/RECORD
