Metadata-Version: 2.4
Name: pandadock
Version: 2.6.0
Summary: Next-Generation Molecular Docking with Novel PandaDock Algorithms
Home-page: https://github.com/pritampanda15/pandadock
Author: Pritam Kumar Panda
Author-email: Pritam Kumar Panda <pritam@stanford.edu>
Maintainer-email: Pritam Kumar Panda <pritam@stanford.edu>
License: MIT
Project-URL: Homepage, https://github.com/pritampanda15/PandaDock
Project-URL: Documentation, https://pandadock.readthedocs.io/
Project-URL: Repository, https://github.com/pritampanda15/PandaDock.git
Project-URL: Bug Tracker, https://github.com/pritampanda15/PandaDock/issues
Project-URL: Source Code, https://github.com/pritampanda15/PandaDock
Project-URL: Changelog, https://github.com/pritampanda15/PandaDock/blob/main/CHANGELOG.md
Keywords: molecular docking,drug discovery,computational chemistry,protein-ligand binding,virtual screening,machine learning,genetic algorithm,physics-based modeling
Classifier: Development Status :: 4 - Beta
Classifier: Intended Audience :: Science/Research
Classifier: License :: OSI Approved :: MIT License
Classifier: Operating System :: OS Independent
Classifier: Programming Language :: Python :: 3
Classifier: Programming Language :: Python :: 3.8
Classifier: Programming Language :: Python :: 3.9
Classifier: Programming Language :: Python :: 3.10
Classifier: Programming Language :: Python :: 3.11
Classifier: Programming Language :: Python :: 3.12
Classifier: Topic :: Scientific/Engineering :: Chemistry
Classifier: Topic :: Scientific/Engineering :: Bio-Informatics
Classifier: Topic :: Scientific/Engineering :: Artificial Intelligence
Requires-Python: >=3.8
License-File: LICENSE
Requires-Dist: numpy>=1.21.0
Requires-Dist: scipy>=1.7.0
Requires-Dist: pandas>=1.3.0
Requires-Dist: scikit-learn>=1.0.0
Requires-Dist: matplotlib>=3.5.0
Requires-Dist: seaborn>=0.11.0
Requires-Dist: pyyaml>=5.4.0
Requires-Dist: click>=8.0.0
Requires-Dist: tqdm>=4.62.0
Requires-Dist: psutil>=5.8.0
Requires-Dist: requests>=2.25.0
Requires-Dist: plotly>=5.0.0
Requires-Dist: h5py>=3.1.0
Requires-Dist: joblib>=1.1.0
Provides-Extra: ml
Requires-Dist: torch>=1.9.0; extra == "ml"
Requires-Dist: torch-geometric>=2.0.0; extra == "ml"
Requires-Dist: transformers>=4.0.0; extra == "ml"
Requires-Dist: xgboost>=1.5.0; extra == "ml"
Provides-Extra: chem
Requires-Dist: rdkit>=2022.03.1; extra == "chem"
Requires-Dist: biopython>=1.79; extra == "chem"
Requires-Dist: openmm>=7.7.0; extra == "chem"
Provides-Extra: viz
Requires-Dist: py3dmol>=1.8.0; extra == "viz"
Requires-Dist: nglview>=3.0.0; extra == "viz"
Requires-Dist: bokeh>=2.4.0; extra == "viz"
Provides-Extra: gpu
Requires-Dist: cupy-cuda11x>=9.0.0; platform_system != "Darwin" and extra == "gpu"
Provides-Extra: web
Requires-Dist: flask>=2.0.0; extra == "web"
Requires-Dist: fastapi>=0.70.0; extra == "web"
Requires-Dist: uvicorn>=0.15.0; extra == "web"
Provides-Extra: dev
Requires-Dist: pytest>=7.0.0; extra == "dev"
Requires-Dist: pytest-cov>=4.0.0; extra == "dev"
Requires-Dist: pytest-xdist>=3.0.0; extra == "dev"
Requires-Dist: black>=22.0.0; extra == "dev"
Requires-Dist: flake8>=5.0.0; extra == "dev"
Requires-Dist: mypy>=1.0.0; extra == "dev"
Requires-Dist: pre-commit>=2.20.0; extra == "dev"
Requires-Dist: ruff>=0.1.0; extra == "dev"
Provides-Extra: docs
Requires-Dist: sphinx>=5.0.0; extra == "docs"
Requires-Dist: sphinx-rtd-theme>=1.2.0; extra == "docs"
Requires-Dist: sphinx-autodoc-typehints>=1.19.0; extra == "docs"
Requires-Dist: myst-parser>=0.18.0; extra == "docs"
Requires-Dist: sphinx-copybutton>=0.5.0; extra == "docs"
Provides-Extra: test
Requires-Dist: pytest>=7.0.0; extra == "test"
Requires-Dist: pytest-cov>=4.0.0; extra == "test"
Requires-Dist: pytest-xdist>=3.0.0; extra == "test"
Requires-Dist: pytest-mock>=3.8.0; extra == "test"
Requires-Dist: coverage[toml]>=6.0.0; extra == "test"
Provides-Extra: all
Requires-Dist: pandadock[chem,gpu,ml,viz,web]; extra == "all"
Dynamic: author
Dynamic: home-page
Dynamic: license-file
Dynamic: requires-python
